rtl/dpd/tddctl.sv
module tddctl(
    input  wire clk, rst,
    input  wire tdd_en, tdd_tx,
    input  wire trigger,
    output wire we,
    output reg start
);
    enum  {Idle, WaitTdd} state = Idle;
    logic trigger_r = 0;
    wire trigger_posedge = ~trigger_r && trigger;

    assign we = (tdd_en & tdd_tx) | ~tdd_en;
    
    always_ff @(posedge clk or posedge rst) begin
        if (rst) trigger_r <= 1'b0;
        else     trigger_r <= trigger;
    end
    
    always_ff @(posedge clk or posedge rst) begin
        if (rst) begin 
            state        <= Idle;
            start        <= 0;
        end else case (state)
            Idle: if (trigger_posedge) begin
                if (tdd_en && ~tdd_tx) state <= WaitTdd;
                else start <= 1;
            end else start <= 0;
            WaitTdd: if (tdd_tx || ~tdd_en) begin
                start <= 1;
                state <= Idle;
            end else start <= 0;
            default: begin
                state <= Idle;
                start <= 0;
            end
        endcase 
    end
endmodule

sim/testbenches/dpd/tddctl_tb.sv
`timescale 1ns/1ps

module tddctl_tb();
    parameter integer CLK_PERIOD = 10;
    parameter reg PRINT = 1;
    logic tb_result = 1;
    
    reg clk, rst;
    reg tdd_tx;
    reg tdd_en;
    reg trigger;
    wire we;
    wire start;
    
    tddctl tddctl (
    	.clk(clk), .rst(rst),
    	.tdd_tx (tdd_tx),
    	.tdd_en (tdd_en),
    	.trigger(trigger),
    	.we     (we),
    	.start  (start)
    );
    
    initial clk = 0;
    always #(CLK_PERIOD/2) clk = ~clk;
    task print_uut();
        $display("  tdd_en = %b; tdd_tx = %b; trigger = %b; we: %b; start: %b;", 
            tdd_en, tdd_tx, trigger, we, start
        );
    endtask
    task set_uut(input en, tx, trig, input print = 0);
        
        tdd_en = en; tdd_tx = tx; trigger = trig;
        if (print) print_uut();
    endtask

    task test_truth_table_row(input en, input tx, input e_we, input e_start);
        @(negedge clk) set_uut(en, tx, 1);
        @(posedge clk);
        @(negedge clk) set_uut(0, 0, 0);
        
        tb_result &= (we == e_we) && (start == e_start);

        if (we == e_we && start == e_start) begin
            $display("||   %b    |   %b    ||  %b  |   %b   |: OK", en, tx, we, start);
        end else begin
            $display("||   %b    |   %b    ||  %b  |   %b   |: FAILED(Expected: we == %b && start == %b)", 
                en, tx, we, start, e_we, e_start
            );
        end
    endtask
    
    task test_trigger_delegation (
        string s0, s1,
        reg end_state [2]
    );
        $display("--%s -> %s--", s0, s1);
        @(negedge clk) set_uut(1, 0, 1, PRINT); // Actiavting trigger
        @(negedge clk) set_uut(1, 0, 0, PRINT); // Releasing trigger
        
        $display("  Delaying for a few cycles...");
        repeat(5) @(negedge clk) tb_result &= ~start;
        
        $display("  Setting %s", s1);
        @(negedge clk) set_uut(end_state[0], end_state[1], 0, PRINT);
        
        $display("  Result:");
        @(negedge clk) set_uut(0, 0, 0, PRINT);
        
        tb_result &= start;
    endtask
    
    
    initial begin
        tdd_en = 0; tdd_tx = 0; trigger = 0;
        rst = 1;
        @(posedge clk)
        rst = 0;
        @(posedge clk)

        $display("Testing truth table");
        $display("|| tdd_en | tdd_tx || we  | start ||");
        test_truth_table_row(0, 0, 1, 1);
        test_truth_table_row(0, 1, 1, 1);
        test_truth_table_row(1, 0, 0, 0);
        test_truth_table_row(1, 1, 1, 1);
        @(posedge clk);

        $display("Testing trigger delegation");
        test_trigger_delegation("tdd_tx=off", "tdd_tx=on", {1, 1});
        test_trigger_delegation("tdd_en=on", "tdd_en=off", {0, 0});
        @(posedge clk);
        
        if (tb_result) $display("Testbench Result: OK");
        else           $display("Testbench Result: FAILED");
        $stop;
    end

    initial begin
        $dumpfile("sim/waveforms/dpd/tddctl.vcd");
        $dumpvars(0, tddctl_tb);
    end

endmodule

sim/waveforms/dpd/tddctl.vcd
$date
	Mon Jun 15 16:41:37 2026
$end
$version
	ModelSim Version 2020.1
$end
$timescale
	1ps
$end

$scope module tddctl_tb $end
$var parameter 32 ! CLK_PERIOD $end
$var parameter 1 " PRINT $end
$var reg 1 # tb_result $end
$var reg 1 $ clk $end
$var reg 1 % rst $end
$var reg 1 & tdd_tx $end
$var reg 1 ' tdd_en $end
$var reg 1 ( trigger $end
$var wire 1 ) we $end
$var wire 1 * start $end

$scope task print_uut $end
$upscope $end

$scope task set_uut $end
$var reg 1 + en $end
$var reg 1 , tx $end
$var reg 1 - trig $end
$var reg 1 . print $end
$upscope $end

$scope task test_truth_table_row $end
$var reg 1 / en $end
$var reg 1 0 tx $end
$var reg 1 1 e_we $end
$var reg 1 2 e_start $end
$upscope $end

$scope task test_trigger_delegation $end
$upscope $end

$scope module tddctl $end
$var wire 1 3 clk $end
$var wire 1 4 rst $end
$var wire 1 5 tdd_en $end
$var wire 1 6 tdd_tx $end
$var wire 1 7 trigger $end
$var wire 1 ) we $end
$var reg 1 8 start $end
$var integer 32 9 state $end
$var reg 1 : trigger_r $end
$var wire 1 ; trigger_posedge $end
$upscope $end
$upscope $end
$enddefinitions $end
#0
$dumpvars
1#
0$
1%
0&
0'
0(
08
0:
x+
x,
x-
x.
x/
x0
x1
x2
b1010 !
b1 "
b0 9
1)
0*
0;
03
14
06
05
07
$end
#5000
1$
13
0%
04
#10000
0$
03
#15000
1$
13
0/
00
11
12
#20000
0$
03
0+
0,
1-
0.
1(
17
1;
#25000
1$
13
1:
18
0;
1*
#30000
0$
03
0-
0(
10
07
#35000
1$
13
0:
08
0*
#40000
0$
03
1,
1-
1&
1(
16
17
1;
#45000
1$
13
1:
18
0;
1*
#50000
0$
03
0,
0-
0&
0(
1/
00
01
02
06
07
#55000
1$
13
0:
08
0*
#60000
0$
03
1+
1-
1'
1(
15
17
0)
1;
#65000
1$
13
1:
b1 9
0;
#70000
0$
03
0+
0-
0'
0(
10
11
12
05
07
1)
#75000
1$
13
0:
18
b0 9
1*
#80000
0$
03
1+
1,
1-
1'
1&
1(
15
16
17
1;
#85000
1$
13
1:
0;
#90000
0$
03
0+
0,
0-
0'
0&
0(
05
06
07
#95000
1$
13
0:
08
0*
#100000
0$
03
1+
1-
1.
1'
1(
15
17
0)
1;
#105000
1$
13
1:
b1 9
0;
#110000
0$
03
0-
0(
07
#115000
1$
13
0:
#120000
0$
03
#125000
1$
13
#130000
0$
03
#135000
1$
13
#140000
0$
03
#145000
1$
13
#150000
0$
03
#155000
1$
13
#160000
0$
03
#165000
1$
13
#170000
0$
03
1,
1&
16
1)
#175000
1$
13
18
b0 9
1*
#180000
0$
03
0+
0,
0'
0&
05
06
#185000
1$
13
08
0*
#190000
0$
03
1+
1-
1'
1(
15
17
0)
1;
#195000
1$
13
1:
b1 9
0;
#200000
0$
03
0-
0(
07
#205000
1$
13
0:
#210000
0$
03
#215000
1$
13
#220000
0$
03
#225000
1$
13
#230000
0$
03
#235000
1$
13
#240000
0$
03
#245000
1$
13
#250000
0$
03
#255000
1$
13
#260000
0$
03
0+
0'
05
1)
#265000
1$
13
18
b0 9
1*
